surfercid/__init__.py
surfercid/client.py
surfercid/models.py
surfercid_client-0.1.49.dist-info/METADATA
surfercid_client-0.1.49.dist-info/WHEEL
surfercid_client-0.1.49.dist-info/top_level.txt
surfercid_client-0.1.49.dist-info/RECORD
